discordproxy/__init__.py
discordproxy/_api.py
discordproxy/_cli.py
discordproxy/_config.py
discordproxy/_constants.py
discordproxy/_decorators.py
discordproxy/_discord_client.py
discordproxy/_server.py
discordproxy/client.py
discordproxy/discord_api_pb2.py
discordproxy/discord_api_pb2_grpc.py
discordproxy/exceptions.py
discordproxy/helpers.py
discordproxy/tests/__init__.py
discordproxy/tests/factories.py
discordproxy/tests/helpers.py
discordproxy/tests/stubs.py
discordproxy/tests/test_api.py
discordproxy/tests/test_cli.py
discordproxy/tests/test_client.py
discordproxy/tests/test_config.py
discordproxy/tests/test_end2end.py
discordproxy/tests/test_exceptions.py
discordproxy/tests/test_helpers.py
discordproxy/tests/test_server.py
discordproxy-1.4.0.dist-info/entry_points.txt
discordproxy-1.4.0.dist-info/licenses/LICENSE
discordproxy-1.4.0.dist-info/WHEEL
discordproxy-1.4.0.dist-info/METADATA
discordproxy-1.4.0.dist-info/RECORD
