Metadata-Version: 2.4
Name: discordproxy
Version: 1.4.0
Summary: Proxy server for accessing the Discord API via gRPC.
Author-email: Erik Kalkoken <kalkoken87@gmail.com>
Requires-Python: >=3.9
Classifier: Intended Audience :: Developers
Classifier: License :: OSI Approved :: MIT License
Classifier: Operating System :: OS Independent
Classifier: Programming Language :: Python
Classifier: Programming Language :: Python :: 3.9
Classifier: Programming Language :: Python :: 3.10
Classifier: Programming Language :: Python :: 3.11
Classifier: Programming Language :: Python :: 3.12
License-File: LICENSE
Requires-Dist: grpcio-tools!=1.45.0
Requires-Dist: py-cord>=2
Requires-Dist: protobuf>=6
Project-URL: Documentation, https://django-eveuniverse.readthedocs.io/en/latest/
Project-URL: Source, https://gitlab.com/ErikKalkoken/discordproxy
Project-URL: Tracker, https://gitlab.com/ErikKalkoken/discordproxy/issues
